yolodetection/__init__.py
yolodetection/instance.py
yolodetection/model_provider.py
yolodetection/predict.py
yolodetection-1.0.12.dist-info/METADATA
yolodetection-1.0.12.dist-info/WHEEL
yolodetection-1.0.12.dist-info/top_level.txt
yolodetection-1.0.12.dist-info/RECORD
