Metadata-Version: 2.4
Name: yolodetection
Version: 1.0.12
Summary: Yolo + sahi toolkit
Author-email: Maxime Phaneuf <maxime.phaneuf@chaac.tech>
License: MIT
Requires-Python: >=3.8
Requires-Dist: pathlib
Requires-Dist: ultralytics
Requires-Dist: sahi
